LICENSE
MANIFEST.in
Makefile
README.rst
adaptor.cpp
lanms.h
setup.py
include/clipper/clipper.cpp
include/clipper/clipper.hpp
include/pybind11/attr.h
include/pybind11/buffer_info.h
include/pybind11/cast.h
include/pybind11/chrono.h
include/pybind11/class_support.h
include/pybind11/common.h
include/pybind11/complex.h
include/pybind11/descr.h
include/pybind11/eigen.h
include/pybind11/embed.h
include/pybind11/eval.h
include/pybind11/functional.h
include/pybind11/numpy.h
include/pybind11/operators.h
include/pybind11/options.h
include/pybind11/pybind11.h
include/pybind11/pytypes.h
include/pybind11/stl.h
include/pybind11/stl_bind.h
include/pybind11/typeid.h
lanms/__init__.py
lanms/adaptor.so
lanms.egg-info/PKG-INFO
lanms.egg-info/SOURCES.txt
lanms.egg-info/dependency_links.txt
lanms.egg-info/requires.txt
lanms.egg-info/top_level.txt